{
    "datetime": 1643710372,
    "donate_url": "",
    "error": false,
    "filehash": "",
    "filename": "",
    "forum_url": "xda_forum_url",
    "id": "",
    "maintainer": "eg: Sushrut1101",
    "maintainer_url": "Maintainer's XDA/Telegram/GitHub (or whatever) URL",
    "news_url": "https://t.me/RavenOSOfficial",
    "size": 1572864,
    "telegram_username": "eg: Inferno964",
    "url": "https://sourceforge.net/projects/raven-os/files/<device>/<filename>/download",
    "version": "twelve",
    "website_url": "https://ravenos.xyz"
}
